pyetheroll/__init__.py
pyetheroll/constants.py
pyetheroll/etheroll.py
pyetheroll/etherscan_utils.py
pyetheroll/transaction_debugger.py
pyetheroll/utils.py
pyetheroll-20200527.dist-info/LICENSE
pyetheroll-20200527.dist-info/METADATA
pyetheroll-20200527.dist-info/WHEEL
pyetheroll-20200527.dist-info/dependency_links.txt
pyetheroll-20200527.dist-info/top_level.txt
pyetheroll-20200527.dist-info/RECORD
