Metadata-Version: 2.1
Name: pyetheroll
Version: 20200527
Summary: Python library to Etheroll smart contract
Home-page: https://github.com/AndreMiras/pyetheroll
Author: Andre Miras
License: UNKNOWN
Platform: UNKNOWN
Requires-Dist: eth-account (<0.5)
Requires-Dist: eth-utils
Requires-Dist: py-etherscan-api (==0.8.0)
Requires-Dist: pycryptodome
Requires-Dist: requests-cache
Requires-Dist: rlp
Requires-Dist: web3 (<6)
